README.rst
setup.py
getTimer/__init__.py
getTimer.egg-info/PKG-INFO
getTimer.egg-info/SOURCES.txt
getTimer.egg-info/dependency_links.txt
getTimer.egg-info/top_level.txt
getTimer/resources/__init__.py
getTimer/resources/getTimerDate.py
getTimer/resources/getTimerDateTime.py
getTimer/resources/getTimerTime.py
getTimer/resources/main.py