Metadata-Version: 1.1
Name: getTimer
Version: 0.1.1
Summary: Get python datetime objects from CLI users easily
Home-page: https://github.com/maxwellgerber/getTimer
Author: Maxwell Gerber
Author-email: maxwell.gerber42@gmail.com
License: MIT
Platform: UNKNOWN
Classifier: Development Status :: 3 - Alpha
Classifier: Intended Audience :: Developers
Classifier: Topic :: System :: Shells
Classifier: Topic :: System :: System Shells
Classifier: Environment :: Console :: Curses
Classifier: License :: OSI Approved :: MIT License
Classifier: Programming Language :: Python :: 2
Classifier: Programming Language :: Python :: 2.6
Classifier: Programming Language :: Python :: 2.7
Classifier: Programming Language :: Python :: 3
Classifier: Programming Language :: Python :: 3.2
Classifier: Programming Language :: Python :: 3.3
Classifier: Programming Language :: Python :: 3.4
Classifier: Programming Language :: Python :: 3.5
